objlog/Base/LogMessage.py
objlog/Base/LogNode.py
objlog/Base/__init__.py
objlog/Base/internal.py
objlog/LogMessages.py
objlog/__init__.py
objlog/constants.py
objlog/utils.py
objlog-3.0.5.dist-info/METADATA
objlog-3.0.5.dist-info/WHEEL
objlog-3.0.5.dist-info/licenses/LICENSE
objlog-3.0.5.dist-info/RECORD
