Metadata-Version: 2.4
Name: ObjLog
Version: 3.0.5
Summary: Logging, Objectified.
License-Expression: Zlib
License-File: LICENSE
Keywords: logging,object,objectified,log,logger,loggers,OOP,python,python3,python3.10,python3.11,python3.12
Author: Kokonico
Author-email: kokonico@duck.com
Requires-Python: >=3.10
Classifier: Topic :: Software Development :: Libraries :: Python Modules
Project-URL: Documentation, https://objlog.rtfd.io/
Project-URL: Repository, https://github.com/Kokonico/ObjLog
